acdh_abbr_client/__init__.py
acdh_abbr_client/acdh_abbr_client.py
acdh_abbr_client/cli.py
acdh_abbr_client-0.2.0.dist-info/AUTHORS.rst
acdh_abbr_client-0.2.0.dist-info/LICENSE
acdh_abbr_client-0.2.0.dist-info/METADATA
acdh_abbr_client-0.2.0.dist-info/WHEEL
acdh_abbr_client-0.2.0.dist-info/entry_points.txt
acdh_abbr_client-0.2.0.dist-info/top_level.txt
acdh_abbr_client-0.2.0.dist-info/RECORD
