Metadata-Version: 2.1
Name: acdh-abbr-client
Version: 0.2.0
Summary: A python client to interact with abbr.acdh.oeaw.ac.at
Home-page: https://github.com/acdh-oeaw/acdh_abbr_client
Author: Peter Andorfer
Author-email: peter.andorfer@oeaw.ac.at
License: MIT license
Keywords: acdh_abbr_client
Platform: UNKNOWN
Classifier: Development Status :: 2 - Pre-Alpha
Classifier: Intended Audience :: Developers
Classifier: License :: OSI Approved :: MIT License
Classifier: Natural Language :: English
Classifier: Programming Language :: Python :: 3.8
Requires-Python: >=3.6
Requires-Dist: Click (>=7.0)
Requires-Dist: requests (==2.25.0)
